README.txt
setup.cfg
setup.py
Products/__init__.py
Products.AnonPAS.egg-info/PKG-INFO
Products.AnonPAS.egg-info/SOURCES.txt
Products.AnonPAS.egg-info/dependency_links.txt
Products.AnonPAS.egg-info/entry_points.txt
Products.AnonPAS.egg-info/namespace_packages.txt
Products.AnonPAS.egg-info/not-zip-safe
Products.AnonPAS.egg-info/requires.txt
Products.AnonPAS.egg-info/top_level.txt
Products/AnonPAS/README
Products/AnonPAS/__init__.py
Products/AnonPAS/config.py
Products/AnonPAS/permissions.py
Products/AnonPAS/version.txt
Products/AnonPAS/Extensions/Install.py
Products/AnonPAS/plugins/.cvsignore
Products/AnonPAS/plugins/__init__.py
Products/AnonPAS/plugins/anoncookie_handler.py
Products/AnonPAS/plugins/www/AnonCookieForm.dtml
docs/HISTORY.txt