Metadata-Version: 1.0
Name: Products.AnonPAS
Version: 1.1-r55
Summary: this plugin can be used for anonymous content submission
Home-page: http://www.gw20e.com
Author: Huub Bouma
Author-email: info@gw20e.com
License: GPL
Platform: UNKNOWN
Classifier: Programming Language :: Python
Classifier: Topic :: Software Development :: Libraries :: Python Modules
